AiogramLegacy/__init__.py
AiogramLegacy/questioning/__init__.py
AiogramLegacy/questioning/questions.py
AiogramLegacy/questioning/questions_manager.py
AiogramLegacy/storages/__init__.py
AiogramLegacy/storages/mysql.py
AiogramLegacy/storages/postgresql.py
AiogramLegacy/storages/sqlite.py
AiogramLegacy-1.0.0.dist-info/METADATA
AiogramLegacy-1.0.0.dist-info/WHEEL
AiogramLegacy-1.0.0.dist-info/top_level.txt
AiogramLegacy-1.0.0.dist-info/RECORD
